maxconsole.py
maxconsole-0.5.1.dist-info/WHEEL
maxconsole-0.5.1.dist-info/METADATA
maxconsole-0.5.1.dist-info/RECORD
