Metadata-Version: 2.1
Name: maxconsole
Version: 0.5.1
Summary: MaxConsole instantiates a customizable themed wrapper around the awesome Rich Library's Console.
License: MIT
Author-email: maxludden <dev@maxludden.com>
Requires-Python: >=3.10
Requires-Dist: rich>=12.6.0
